schema_graph/__init__.py
schema_graph/schema.py
schema_graph/static/schema_graph/.empty-file
schema_graph/static/schema_graph/main.js
schema_graph/templates/schema_graph/schema.html
schema_graph/views.py
django_schema_graph-3.0.0.dist-info/LICENSE
django_schema_graph-3.0.0.dist-info/METADATA
django_schema_graph-3.0.0.dist-info/WHEEL
django_schema_graph-3.0.0.dist-info/RECORD
