Metadata-Version: 2.1
Name: django-schema-graph
Version: 3.0.0
Summary: An interactive graph of your Django model structure.
Home-page: https://github.com/meshy/django-schema-graph
License: MIT
Author: Charlie Denton
Author-email: charlie@meshy.co.uk
Requires-Python: >=3.10
Classifier: Development Status :: 4 - Beta
Classifier: Framework :: Django
Classifier: Framework :: Django :: 3.2
Classifier: Framework :: Django :: 4.0
Classifier: Framework :: Django :: 4.1
Classifier: Intended Audience :: Developers
Classifier: License :: OSI Approved :: MIT License
Classifier: Natural Language :: English
Classifier: Programming Language :: Python
Classifier: Programming Language :: Python :: 3
Classifier: Programming Language :: Python :: 3.10
Classifier: Programming Language :: Python :: 3.11
Classifier: Programming Language :: Python :: 3
Classifier: Programming Language :: Python :: 3.10
Classifier: Programming Language :: Python :: 3.11
Classifier: Topic :: Database
Classifier: Topic :: Documentation
Classifier: Topic :: Utilities
Requires-Dist: attrs (>=21.4.0)
Requires-Dist: cattrs (>=22.1.0)
Project-URL: Repository, https://github.com/meshy/django-schema-graph
